stream_inflate.cpython-38-x86_64-linux-gnu.so
stream_inflate.py
stream_inflate-0.0.42.dist-info/LICENSE
stream_inflate-0.0.42.dist-info/METADATA
stream_inflate-0.0.42.dist-info/WHEEL
stream_inflate-0.0.42.dist-info/top_level.txt
stream_inflate-0.0.42.dist-info/RECORD
