Metadata-Version: 2.4
Name: stream-inflate
Version: 0.0.42
Summary: Uncompress DEFLATE streams in pure Python (albeit compiled with Cython)
Author-email: Michal Charemza <michal@charemza.name>
Project-URL: Source, https://github.com/michalc/stream-inflate
Classifier: Programming Language :: Python :: 3
Classifier: License :: OSI Approved :: MIT License
Classifier: Topic :: System :: Archiving :: Compression
Requires-Python: >=3.7.7
License-File: LICENSE
Provides-Extra: dev
Requires-Dist: coverage>=6.2; extra == "dev"
Requires-Dist: pytest>=6.2.5; extra == "dev"
Requires-Dist: pytest-cov>=3.0.0; extra == "dev"
Requires-Dist: Cython>=3.0.0; extra == "dev"
Requires-Dist: setuptools; extra == "dev"
Requires-Dist: build; extra == "dev"
Dynamic: license-file
